wfdb_to_csv/__init__.py
wfdb_to_csv/cli.py
wfdb_to_csv/core.py
wfdb_to_csv-0.1.1.dist-info/METADATA
wfdb_to_csv-0.1.1.dist-info/WHEEL
wfdb_to_csv-0.1.1.dist-info/entry_points.txt
wfdb_to_csv-0.1.1.dist-info/top_level.txt
wfdb_to_csv-0.1.1.dist-info/RECORD
