Metadata-Version: 2.4
Name: wfdb_to_csv
Version: 0.1.1
Summary: Convert WFDB ECG (.hea/.dat) to CSV with UNIX epoch nanosecond timestamps
Home-page: https://github.com/barthwalsaurabh0/wfdb_to_csv
License: MIT
Classifier: Programming Language :: Python :: 3
Classifier: License :: OSI Approved :: MIT License
Classifier: Operating System :: OS Independent
Requires-Python: >=3.8
Requires-Dist: wfdb
Requires-Dist: pandas
Requires-Dist: tqdm
